{

	"aEP_FSF":{
		"hyperspaceJitterColor":[255,145,75,200],
		"baseCampaignExplosionColor":[255,145,75,255],
		"baseCombatExplosionColor":[255,145,75,255],
		"fighterRepairFlickerColor":[255,145,75,255],
		"fighterChipIconColor":[255,255,255,255],
		"weaponDisabledExplosionColor":[255,111,81,255],
		"shieldRingColor":[185,45,45,245],
		"shieldInnerColor":[145,65,65,165],
		"fluxVentCoreColor":[255,255,255,255],
		"fluxVentFringeColor":[155,55,55,255],
		"fluxVentTextureSheet":"graphics/aEP_hullstyle/vent.png", # optional, this is the default value
		#"fluxVentTextureSheet":"graphics/fx/portal_textures_small.png",
		#"fluxVentTextureSheet":"graphics/fx/fx_clouds00.png",
		"engineLoopSet":"engine_loop", 					# id of entry in sounds.json
		"engineAccelerateSet":"engine_accelerate",		# id of entry in sounds.json
		"empLoopSet":"emp_loop",						# id of entry in sounds.json
		"fluxLoopSet":"flux_loop",						# id of entry in sounds.json
		"ventFluxSet":"vent_flux",						# id of entry in sounds.json
		"shieldBurnoutSet":"shield_burnout",			# id of entry in sounds.json
		"shieldLowerSet":"shield_lower",				# id of entry in sounds.json
		"shieldRaiseSet":"shield_raise",				# id of entry in sounds.json
		"explosionShipSet":"explosion_ship",			# id of entry in sounds.json
		"damageDecalSheet":"graphics/damage/damage_decal_sheet_base.png",
		"damageDecalGlowSheet":"graphics/damage/damage_decal_sheet_glow.png",
		
		"colorShiftCovers":true,
		"coversColorShiftAmount":0.2,  # 0 to 1
		"coversMatchShipBrightness":true,
		"slotCoverSmallTurret":"graphics/aEP_hullstyle/small_tr_cover.png",
		"slotCoverSmallHardpoint":"graphics/aEP_hullstyle/small_hp_cover.png",
		"slotCoverMediumTurret":"graphics/weapons/covers/cover_turret_midline_medium.png",
		"slotCoverMediumHardpoint":"graphics/weapons/covers/cover_hardpoint_midline_medium.png",
		"slotCoverLargeTurret":"graphics/weapons/covers/cover_turret_midline_large.png",
		"slotCoverLargeHardpoint":"graphics/weapons/covers/cover_hardpoint_midline_large.png",
		
		"dHullOverlayLight":"graphics/damage/dmod_overlay_midline_light.png",
		"dHullOverlayMedium":"graphics/damage/dmod_overlay_midline_medium.png",
		"dHullOverlayHeavy":"graphics/damage/dmod_overlay_midline_heavy.png",
	},	


	
}